salt_gnupg_rotate/__init__.py
salt_gnupg_rotate/cli.py
salt_gnupg_rotate/config.py
salt_gnupg_rotate/exceptions.py
salt_gnupg_rotate/logger.py
salt_gnupg_rotate/logging_mixins.py
salt_gnupg_rotate/main.py
salt_gnupg_rotate/rotate.py
salt_gnupg_rotate-1.3.2.dist-info/LICENSE
salt_gnupg_rotate-1.3.2.dist-info/METADATA
salt_gnupg_rotate-1.3.2.dist-info/WHEEL
salt_gnupg_rotate-1.3.2.dist-info/entry_points.txt
salt_gnupg_rotate-1.3.2.dist-info/RECORD
