Metadata-Version: 2.1
Name: salt-gnupg-rotate
Version: 1.3.2
Summary: Easily rotate gnupg encryption keys of fully or partially encrypted files.
Home-page: https://github.com/raddessi/salt-gnupg-rotate
License: BSD 2-Clause 'Simplified' License
Author: Ryan Addessi
Author-email: raddessi@users.noreply.github.com
Requires-Python: >=3.8,<4.0
Classifier: License :: Other/Proprietary License
Classifier: Programming Language :: Python :: 3
Classifier: Programming Language :: Python :: 3.8
Classifier: Programming Language :: Python :: 3.9
Classifier: Programming Language :: Python :: 3.10
Classifier: Programming Language :: Python :: 3.11
Classifier: Programming Language :: Python :: 3.12
Requires-Dist: click (>=8.1.7,<9.0.0)
Requires-Dist: python-gnupg (>=0.5.2)
Requires-Dist: rich (>=13.7.1)
Requires-Dist: sphinx-click (>=6.0.0,<7.0.0)
Project-URL: Changelog, https://github.com/raddessi/salt-gnupg-rotate/releases
Project-URL: Repository, https://github.com/raddessi/salt-gnupg-rotate
